MANIFEST.in
README
setup.py
cacete/lib/python3.7/site-packages/easy_install.py
cacete/lib/python3.7/site-packages/pip/__init__.py
cacete/lib/python3.7/site-packages/pip/__main__.py
cacete/lib/python3.7/site-packages/pip-19.0.3.dist-info/LICENSE.txt
cacete/lib/python3.7/site-packages/pip-19.0.3.dist-info/entry_points.txt
cacete/lib/python3.7/site-packages/pip-19.0.3.dist-info/top_level.txt
cacete/lib/python3.7/site-packages/pip/_internal/__init__.py
cacete/lib/python3.7/site-packages/pip/_internal/build_env.py
cacete/lib/python3.7/site-packages/pip/_internal/cache.py
cacete/lib/python3.7/site-packages/pip/_internal/configuration.py
cacete/lib/python3.7/site-packages/pip/_internal/download.py
cacete/lib/python3.7/site-packages/pip/_internal/exceptions.py
cacete/lib/python3.7/site-packages/pip/_internal/index.py
cacete/lib/python3.7/site-packages/pip/_internal/locations.py
cacete/lib/python3.7/site-packages/pip/_internal/pep425tags.py
cacete/lib/python3.7/site-packages/pip/_internal/pyproject.py
cacete/lib/python3.7/site-packages/pip/_internal/resolve.py
cacete/lib/python3.7/site-packages/pip/_internal/wheel.py
cacete/lib/python3.7/site-packages/pip/_internal/cli/__init__.py
cacete/lib/python3.7/site-packages/pip/_internal/cli/autocompletion.py
cacete/lib/python3.7/site-packages/pip/_internal/cli/base_command.py
cacete/lib/python3.7/site-packages/pip/_internal/cli/cmdoptions.py
cacete/lib/python3.7/site-packages/pip/_internal/cli/main_parser.py
cacete/lib/python3.7/site-packages/pip/_internal/cli/parser.py
cacete/lib/python3.7/site-packages/pip/_internal/cli/status_codes.py
cacete/lib/python3.7/site-packages/pip/_internal/commands/__init__.py
cacete/lib/python3.7/site-packages/pip/_internal/commands/check.py
cacete/lib/python3.7/site-packages/pip/_internal/commands/completion.py
cacete/lib/python3.7/site-packages/pip/_internal/commands/configuration.py
cacete/lib/python3.7/site-packages/pip/_internal/commands/download.py
cacete/lib/python3.7/site-packages/pip/_internal/commands/freeze.py
cacete/lib/python3.7/site-packages/pip/_internal/commands/hash.py
cacete/lib/python3.7/site-packages/pip/_internal/commands/help.py
cacete/lib/python3.7/site-packages/setuptools-40.8.0.dist-info/dependency_links.txt
cacete/lib/python3.7/site-packages/setuptools-40.8.0.dist-info/entry_points.txt
cacete/lib/python3.7/site-packages/setuptools-40.8.0.dist-info/top_level.txt
cacete/lib64/python3.7/site-packages/pip-19.0.3.dist-info/LICENSE.txt
cacete/lib64/python3.7/site-packages/pip-19.0.3.dist-info/entry_points.txt
cacete/lib64/python3.7/site-packages/pip-19.0.3.dist-info/top_level.txt
cacete/lib64/python3.7/site-packages/setuptools-40.8.0.dist-info/dependency_links.txt
cacete/lib64/python3.7/site-packages/setuptools-40.8.0.dist-info/entry_points.txt
cacete/lib64/python3.7/site-packages/setuptools-40.8.0.dist-info/top_level.txt
premirnaplot.egg-info/PKG-INFO
premirnaplot.egg-info/SOURCES.txt
premirnaplot.egg-info/dependency_links.txt
premirnaplot.egg-info/requires.txt
premirnaplot.egg-info/top_level.txt