Metadata-Version: 1.1
Name: premirnaplot
Version: 1.0
Summary: pre-miRNA secondary structure prediction image generator
Home-page: https://github.com/igrorp/pre-miRNA-plot
Author: Igor Paim
Author-email: igorpaim8@gmail.com
License: GPL
Keywords: pre-miRNA
Platform: UNKNOWN
Classifier: Intended Audience :: Science/Research
Classifier: Topic :: Scientific/Engineering :: Bio-Informatics
Classifier: Programming Language :: Python :: 3
